Workbook

Sheet DATA
A3: ASSUMPTIONS:
A4: Annual Asking Rent (P/SQM) | B4: 250 | E4: Metro
A5: Annual Gross Potential Rent Growth (%) | B5: 0.04 | E5: Regional
A6: Annual Expense Growth (%) | B6: 0.025
A7: Net Lettable Area (SQM) | B7: 5000
A8: Land Price | B8: 500000
A9: Construction Cost (P/SQM) | B9: 1500
A10: Other Income (% of NER) | B10: 0.03

Sheet INPUTS
B2: YEAR
A3: REVENUE | B3: 0 | C3: 1 | D3: 2 | E3: 3 | F3: 4 | G3: 5 | H3: 6 | I3: 7 | J3: 8 | K3: 9 | L3: 10
A4: Gross Potential Rent (GPR) | B4: 0 | C4: =DATA!B4*DATA!B7 | D4: =C4*(1+D5) | E4: =D4*(1+E5) | F4: =E4*(1+F5) | G4: =F4*(1+G5) | H4: =G4*(1+H5) | I4: =H4*(1+I5) | J4: =I4*(1+J5) | K4: =J4*(1+K5) | L4: =K4*(1+L5)
A5: GPR Growth (%) | B5: 0 | C5: =DATA!B5 | D5: =DATA!B5 | E5: =DATA!B5 | F5: =DATA!B5 | G5: =DATA!B5 | H5: =DATA!B5 | I5: =DATA!B5 | J5: =DATA!B5 | K5: =DATA!B5 | L5: =DATA!B5
A6: Vacancy Rate | B6: 1 | C6: 1 | D6: 0.55 | E6: 0.1 | F6: 0.1 | G6: 0.1 | H6: 0.1 | I6: 0.1 | J6: 0.1 | K6: 0.1 | L6: 0.1
A7: Occupancy Rate (%) | B7: =1-B6 | C7: =1-C6 | D7: =1-D6 | E7: =1-E6 | F7: =1-F6 | G7: =1-G6 | H7: =1-H6 | I7: =1-I6 | ... L7: =1-L6
A8: Gross Potential Rent (less Vacancy) | B8: =B4-(B4*B6) | C8: =C4-(C4*C6) | D8: =D4-(D4*D6) | E8: =E4-(E4*E6) | F8: =F4-(F4*F6) | G8: =G4-(G4*G6) | H8: =H4-(H4*H6) | I8: =I4-(I4*I6) | ... L8: =L4-(L4*L6)
A9: Discount Rate (%) | B9: 0 | C9: 0.2 | D9: 0.1 | E9: 0.05 | F9: 0.05 | G9: 0.05 | H9: 0.05 | I9: 0.05 | J9: 0.05 | K9: 0.05 | L9: 0.05
A10: Net Effective Rent | B10: =B8/(1+B9)^B3 | C10: =C8/(1+C9)^C3 | D10: =D8/(1+D9)^D3 | E10: =E8/(1+E9)^E3 | F10: =F8/(1+F9)^F3 | G10: =G8/(1+G9)^G3 | H10: =H8/(1+H9)^H3 | I10: =I8/(1+I9)^I3 | ... L10: =L8/(1+L9)^L3
A11: Other Income | B11: =B10*DATA!B10 | C11: =C10*DATA!B10 | D11: =D10*DATA!B10 | E11: =E10*DATA!B10 | F11: =F10*DATA!B10 | G11: =G10*DATA!B10 | H11: =H10*DATA!B10 | I11: =I10*DATA!B10 | J11: =J10*DATA!B10 | K11: =K10*DATA!B10 | L11: =L10*DATA!B10
A12: Total Revenue (Annualised) | B12: =SUM(B10+B11) | C12: =SUM(C10+C11) | D12: =SUM(D10+D11) | E12: =SUM(E10+E11) | F12: =SUM(F10+F11) | G12: =SUM(G10+G11) | H12: =SUM(H10+H11) | I12: =SUM(I10+I11) | ... L12: =SUM(L10+L11)
A13: EXPENSES
A14: Regional
A15: Advertising & Marketing | C15: 3.44 | D15: 3.17 | E15: 4.28 | F15: 4.29 | G15: 0.88
A16: Electricity | C16: 1.24 | D16: 1.8 | E16: 1.78 | F16: 1.4 | G16: 1.72
A17: Insurance
A18: Land Tax
A19: Printing & Postage
A20: Rates
A21: R&M
A22: Salaries & Wages
A23: Telco

Sheet Sheet2
C1: 1 | D1: 2 | E1: 3 | F1: 4 | G1: 5
A3: Regional | B3: Advertising & Marketing | C3: 3.44 | D3: 3.17 | E3: 4.28 | F3: 4.29 | G3: 0.88
A4: Regional | B4: Electricity | C4: 1.24 | D4: 1.8 | E4: 1.78 | F4: 1.4 | G4: 1.72
A5: Regional | B5: Insurance | C5: 2.56 | D5: 2.53 | E5: 1.79 | F5: 2.18 | G5: 2.04
A6: Regional | B6: Land Tax
A7: Regional | B7: Printing & Postage
A8: Regional | B8: Rates
A9: Regional | B9: R&M
A10: Regional | B10: Salaries & Wages
A11: Regional | B11: Telco
A12: Metro | B12: Advertising & Marketing | C12: 9.09 | D12: 7.76 | E12: 8.53 | F12: 6.83 | G12: 3.52
A13: Metro | B13: Electricity
A14: Metro | B14: Insurance
A15: Metro | B15: Land Tax
A16: Metro | B16: Printing & Postage
A17: Metro | B17: Rates
A18: Metro | B18: R&M
A19: Metro | B19: Salaries & Wages
A20: Metro | B20: Telco

Sheet ANNUAL OUTPUT
B2: 1 | C2: 2 | D2: 3 | E2: 4 | F2: 5
A3: Expenses | B3: <12 Months ($/SQM Avg) | C3: 12-24 Months ($/SQM Avg) | D3: 24-36 Months ($/SQM Avg) | E3: 36-48 Months ($/SQM Avg) | F3: 48-60 Months ($/SQM Avg)
A4: Advertising & Marketing
A5: Metro | B5: 9.09 | C5: 7.76 | D5: 8.53 | E5: 6.83 | F5: 3.52
A6: Regional | B6: 3.44 | C6: 3.17 | D6: 4.28 | E6: 4.29 | F6: 0.88
A8: Electricity
A9: Metro | B9: 2.46 | C9: 2.43 | D9: 3.2 | E9: 3.2 | F9: 3.82
A10: Regional | B10: 1.24 | C10: 1.8 | D10: 1.78 | E10: 1.4 | F10: 1.72
A12: Insurance
A13: Metro | B13: 3.9 | C13: 3.03 | D13: 2.66 | E13: 2.58 | F13: 1.92
A14: Regional | B14: 2.56 | C14: 2.53 | D14: 1.79 | E14: 2.18 | F14: 2.04
A16: Land Tax
A17: Metro | B17: 12.64 | C17: 10.55 | D17: 13.08 | E17: 10.1 | F17: 9.58
A18: Regional | B18: 7.06 | C18: 5.64 | D18: 2.02 | E18: 2.2 | F18: 1.85
A20: Printing & Postage
A21: Metro | B21: 0.54 | C21: 0.72 | D21: 0.83 | E21: 0.87 | F21: 0.79
A22: Regional | B22: 0.43 | C22: 0.68 | D22: 0.61 | E22: 0.4 | F22: 1.18
A24: Rates
A25: Metro | B25: 6.69 | C25: 6.26 | D25: 6.89 | E25: 6.25 | F25: 6.49
A26: Regional | B26: 6.33 | C26: 5.69 | D26: 3.95 | E26: 4.78 | F26: 3.42
A28: R&M
A29: Metro | B29: 5.82 | C29: 4.78 | D29: 4.96 | E29: 3.38 | F29: 3.71
A30: Regional | B30: 3.49 | C30: 3.15 | D30: 2.44 | E30: 1.95 | F30: 1.6
A32: Salaries & Wages
A33: Metro | B33: 24.64 | C33: 21.86 | D33: 24.68 | E33: 25.84 | F33: 26.96
A34: Regional | B34: 16.95 | C34: 16.87 | D34: 19.49 | E34: 16.63 | F34: 23.15
A36: Telco
A37: Metro | B37: 1.21 | C37: 1.19 | D37: 1.18 | E37: 0.9 | F37: 1.22
A38: Regional | B38: 0.62 | C38: 0.55 | D38: 0.77 | E38: 0.82 | F38: 0.77
